sginnovate/Preprocessing_opt.py
sginnovate/__init__.py
sginnovate/main.py
sginnovate/mask_saving.py
sginnovate/mrcnn/__init__.py
sginnovate/mrcnn/config.py
sginnovate/mrcnn/model.py
sginnovate/mrcnn/parallel_model.py
sginnovate/mrcnn/utils.py
sginnovate/mrcnn/visualize.py
sputummrcnn-0.9.dist-info/LICENSE.txt
sputummrcnn-0.9.dist-info/METADATA
sputummrcnn-0.9.dist-info/WHEEL
sputummrcnn-0.9.dist-info/top_level.txt
sputummrcnn-0.9.dist-info/RECORD
