Metadata-Version: 2.1
Name: sputummrcnn
Version: 0.9
Summary: Custom Mask RCNN
Home-page: UNKNOWN
License: UNKNOWN
Platform: UNKNOWN
Requires-Python: >=3.6
License-File: LICENSE.txt
Requires-Dist: numpy
Requires-Dist: scipy
Requires-Dist: Pillow
Requires-Dist: cython
Requires-Dist: matplotlib
Requires-Dist: pandas
Requires-Dist: scikit-image
Requires-Dist: tensorflow (==1.15.0)
Requires-Dist: keras (==2.2.4)
Requires-Dist: opencv-python
Requires-Dist: h5py (==2.10.0)
Requires-Dist: imgaug
Requires-Dist: theano
Requires-Dist: IPython[all]
